data2supplymodel/__init__.py
data2supplymodel/data2supply.py
data2supplymodel/field_attachment.py
data2supplymodel/period_setting.py
data2supplymodel/setting.py
data2supplymodel-0.0.3.dist-info/METADATA
data2supplymodel-0.0.3.dist-info/WHEEL
data2supplymodel-0.0.3.dist-info/top_level.txt
data2supplymodel-0.0.3.dist-info/RECORD
