Metadata-Version: 2.1
Name: data2supplymodel
Version: 0.0.3
Summary: The data2supply is a data-driven calibration package for traffic flow model calibration, Bureau of Public Roads (BPR) function calibration, and the queueing characterization for transportation planners, engineers, and researchers.
Home-page: https://github.com/Grieverwzn/data2supplymodel
Author: Xin Wu, Xuesong Zhou
Author-email: xinwu3@asu.edu, xzhou74@asu.edu
License: GPLb3+
Platform: UNKNOWN
Requires-Python: >=3.6.0
Requires-Dist: pandas
Requires-Dist: numpy
Requires-Dist: scipy
Requires-Dist: sklearn
Requires-Dist: matplotlib
